swaggermarkdown/__init__.py
swaggermarkdown/swaggermarkdown.py
tests/__init__.py
tests/test_sw_md.py
swagger_markdown-0.9.1.dist-info/LICENSE
swagger_markdown-0.9.1.dist-info/METADATA
swagger_markdown-0.9.1.dist-info/WHEEL
swagger_markdown-0.9.1.dist-info/top_level.txt
swagger_markdown-0.9.1.dist-info/RECORD
